[
  {
    "name": "espresso maker",
    "description": "I am a coffee addict",
    "url": "https://www.amazon.de/Bialetti-Moka-Express-espresso-maker/dp/B00004RFRU/ref=sr_1_3?__mk_de_DE=%C3%85M%C3%85%C5%BD%C3%95%C3%91&dchild=1&keywords=espresso+maker&qid=1595583426&sr=8-3",
    "category": "baby",
    "guest": {
      "_id": "87654321"
    },
    "wedding": {
      "_id": "1427585207489754589"
    }
  },
  {
    "name": "espresso maker",
    "description": "I am a coffee addict",
    "url": "https://www.amazon.de/Bialetti-Moka-Express-espresso-maker/dp/B00004RFRU/ref=sr_1_3?__mk_de_DE=%C3%85M%C3%85%C5%BD%C3%95%C3%91&dchild=1&keywords=espresso+maker&qid=1595583426&sr=8-3",
    "category": "baby",
    "guest": {
      "_id": "87654321"
    },
    "wedding": {
      "_id": "1427585207489754589"
    }
  }
  ]